ashapipro/__init__.py
ashapipro/__main__.py
ashapipro/autopilot/__init__.py
ashapipro/autopilot/coursekeeper.py
ashapipro/autopilot/regulator.py
ashapipro/autopilot/routekeeper.py
ashapipro/autopilot/speedkeeper.py
ashapipro/routes/__init__.py
ashapipro/routes/areautil.py
ashapipro/routes/graph.py
ashapipro/tutorials/__init__.py
ashapipro/tutorials/content/__init__.py
ashapipro/tutorials/content/content_models.py
ashapipro/tutorials/content/content_recordings.py
ashapipro/tutorials/content/content_scenes.py
ashapipro/tutorials/environment/__init__.py
ashapipro/tutorials/environment/environment_get_current.py
ashapipro/tutorials/environment/environment_get_time.py
ashapipro/tutorials/environment/environment_get_wave.py
ashapipro/tutorials/environment/environment_get_weather.py
ashapipro/tutorials/environment/environment_get_wind.py
ashapipro/tutorials/environment/environment_set_current.py
ashapipro/tutorials/environment/environment_set_time.py
ashapipro/tutorials/environment/environment_set_wave.py
ashapipro/tutorials/environment/environment_set_weather.py
ashapipro/tutorials/environment/environment_set_wind.py
ashapipro/tutorials/objects/__init__.py
ashapipro/tutorials/objects/cargo_keep_course.py
ashapipro/tutorials/objects/cargo_keep_speed.py
ashapipro/tutorials/objects/object_add.py
ashapipro/tutorials/objects/object_count_params.py
ashapipro/tutorials/objects/object_devices_orders.py
ashapipro/tutorials/objects/object_devices_state.py
ashapipro/tutorials/objects/object_get_position.py
ashapipro/tutorials/objects/object_get_speeds.py
ashapipro/tutorials/objects/object_id.py
ashapipro/tutorials/objects/object_remove.py
ashapipro/tutorials/objects/object_set_orders.py
ashapipro/tutorials/objects/object_set_position.py
ashapipro/tutorials/objects/object_set_rotation.py
ashapipro/tutorials/objects/object_set_speed.py
ashapipro/tutorials/objects/object_set_values.py
ashapipro/tutorials/recording/__init__.py
ashapipro/tutorials/recording/recording_open.py
ashapipro-1.0.0.dist-info/LICENSE.txt
ashapipro-1.0.0.dist-info/METADATA
ashapipro-1.0.0.dist-info/WHEEL
ashapipro-1.0.0.dist-info/top_level.txt
ashapipro-1.0.0.dist-info/RECORD
