Metadata-Version: 2.1
Name: ashapipro
Version: 1.0.0
Summary: Python library for SimTech simcomplex (autonomous ship handling emulating system) - with tutorials and examples for ashapi usage
Author-email: Pavel Piontek <pavel.piontek@simtech.spb.ru>, Vasily Zverkov <vasily.zverkov@simtech.spb.ru>
Maintainer-email: Pavel Piontek <pavel.piontek@simtech.spb.ru>, Vasily Zverkov <vasily.zverkov@simtech.spb.ru>
License: GNU GENERAL PUBLIC LICENSE
Project-URL: Homepage, https://www.simtech.spb.ru/ipkas
Project-URL: Source, https://dev.azure.com/simtechspbru/%D0%98%D0%9F%D0%9A%D0%90%D0%A1/_git/ashapi-library
Keywords: autonomous,ship,vessel,mass
Classifier: Development Status :: 5 - Production/Stable
Classifier: Intended Audience :: Science/Research
Classifier: Topic :: Scientific/Engineering :: Interface Engine/Protocol Translator
Classifier: Programming Language :: Python :: 3
Classifier: Programming Language :: Python :: 3.8
Classifier: Programming Language :: Python :: 3.9
Classifier: Programming Language :: Python :: 3.10
Classifier: Programming Language :: Python :: 3.11
Classifier: Programming Language :: Python :: 3.12
Classifier: Programming Language :: Python :: 3 :: Only
Requires-Python: >=3.8
License-File: LICENSE.txt
Requires-Dist: ashapi
Requires-Dist: geopandas
Requires-Dist: networkx
Requires-Dist: folium
Requires-Dist: matplotlib
Requires-Dist: mapclassify
Provides-Extra: dev
Requires-Dist: build ; extra == 'dev'
Requires-Dist: twine ; extra == 'dev'
Provides-Extra: test
Requires-Dist: pytest ; extra == 'test'
